LICENSE
README.md
setup.py
nhanthien3011_test.egg-info/PKG-INFO
nhanthien3011_test.egg-info/SOURCES.txt
nhanthien3011_test.egg-info/dependency_links.txt
nhanthien3011_test.egg-info/entry_points.txt
nhanthien3011_test.egg-info/requires.txt
nhanthien3011_test.egg-info/top_level.txt
src/__init__.py
src/logic.py
src/main.py