Metadata-Version: 2.1
Name: nhanthien3011-test
Version: 0.0.1
Summary: An application that informs you of the time in different locations and timezones
Home-page: https://github.com/nhanth301
Author: Nguyen Thien Nhan
Author-email: nhanthien.tnn@gmail.com
License: UNKNOWN
Platform: UNKNOWN
Classifier: Programming Language :: Python :: 3
Classifier: License :: OSI Approved :: MIT License
Classifier: Operating System :: OS Independent
License-File: LICENSE
